viper/__init__.py
viper/cli.py
viper/cli_base.py
viper/collections.py
viper/const.py
viper/db.py
viper/main.py
viper/project.py
viper/serializers.py
viper/utils.py
viper/demo/__init__.py
viper/demo/actions.py
viper/demo/callbacks.py
viper/demo/commands.py
viper/demo/filters.py
viper/demo/handlers.py
viper/demo/hosts.py
viper/demo/jobs.py
viper/demo/loaders.py
viper/demo/processors.py
viper/demo/sort.py
viper/demo/tasks.py
viper/demo/viperfile.py
viper_infra_commander-0.28.3.dist-info/LICENSE
viper_infra_commander-0.28.3.dist-info/METADATA
viper_infra_commander-0.28.3.dist-info/WHEEL
viper_infra_commander-0.28.3.dist-info/entry_points.txt
viper_infra_commander-0.28.3.dist-info/top_level.txt
viper_infra_commander-0.28.3.dist-info/RECORD
