Metadata-Version: 2.1
Name: viper-infra-commander
Version: 0.28.3
Summary: Viper provides a simple API (Python and CLI) to easily manage large infrastructures.
Home-page: https://github.com/sayanarijit/viper
Author: Arijit Basu
Author-email: sayanarijit@gmail.com
License: MIT
Keywords: viper infrastructure commander
Platform: Any
Classifier: Development Status :: 3 - Alpha
Classifier: Intended Audience :: Developers
Classifier: Intended Audience :: Information Technology
Classifier: Intended Audience :: System Administrators 
Classifier: Intended Audience :: Other Audience
Classifier: License :: OSI Approved :: MIT License
Classifier: Programming Language :: Python :: 3.8
Provides-Extra: autocomplete
Requires-Dist: argcomplete (==1.10.3) ; extra == 'autocomplete'
Provides-Extra: batteries
Requires-Dist: argcomplete (==1.10.3) ; extra == 'batteries'
Requires-Dist: pyyaml (==5.3) ; extra == 'batteries'
Provides-Extra: dev
Requires-Dist: argcomplete (==1.10.3) ; extra == 'dev'
Requires-Dist: pyyaml (==5.3) ; extra == 'dev'
Requires-Dist: pytest (>=4.4.1) ; extra == 'dev'
Requires-Dist: pytest-cov (>=2.7.1) ; extra == 'dev'
Requires-Dist: black (>=19.3b0) ; extra == 'dev'
Requires-Dist: isort (>=4.3.21) ; extra == 'dev'
Requires-Dist: mypy (>=0.710) ; extra == 'dev'
Requires-Dist: lxml (>=4.3.4) ; extra == 'dev'
Requires-Dist: pre-commit (>=1.20.0) ; extra == 'dev'
Requires-Dist: pre-commit-hooks (>=2.4.0) ; extra == 'dev'
Requires-Dist: typecov (>=0.2.1) ; extra == 'dev'
Requires-Dist: tox (>=3.12.1) ; extra == 'dev'
Requires-Dist: twine (>=3.1.1) ; extra == 'dev'
Requires-Dist: sphinx (>=2.2.1) ; extra == 'dev'
Provides-Extra: testing
Requires-Dist: argcomplete (==1.10.3) ; extra == 'testing'
Requires-Dist: pyyaml (==5.3) ; extra == 'testing'
Requires-Dist: pytest (>=4.4.1) ; extra == 'testing'
Requires-Dist: pytest-cov (>=2.7.1) ; extra == 'testing'
Requires-Dist: black (>=19.3b0) ; extra == 'testing'
Requires-Dist: isort (>=4.3.21) ; extra == 'testing'
Requires-Dist: mypy (>=0.710) ; extra == 'testing'
Requires-Dist: lxml (>=4.3.4) ; extra == 'testing'
Requires-Dist: pre-commit (>=1.20.0) ; extra == 'testing'
Requires-Dist: pre-commit-hooks (>=2.4.0) ; extra == 'testing'
Requires-Dist: typecov (>=0.2.1) ; extra == 'testing'
Provides-Extra: yaml
Requires-Dist: pyyaml (==5.3) ; extra == 'yaml'
